Workbook

Sheet Cover
A1: EQUITY RESEARCH – EQUITY GROUP HOLDINGS PLC
A2: Purpose | B2: Equity research project
A3: Company | B3: Equity Group Holdings Plc
A4: Ticker | B4: EQTY (NSE)
A5: Sector | B5: Banking / Financial Services
A6: Research date | B6: Prepared October 2026; valuation as at 31 March 2026
A7: Name | B7: Vivek Divecha
A8: Investment view | B8: =Valuation!E11 -> BUY
A9: Target price | B9: =Valuation!E6 -> 101.96737
A10: Current price | B10: =Valuation!E7 -> 69
A11: Upside / (Downside) | B11: =Valuation!E8 -> 0.47778791
A12: Expected total return (incl. dividend) | B12: =Valuation!E10 -> 0.54678791
A14: INVESTMENT THESIS – 3 POINTS
A15: [1] Earnings / profitability driver | B15: Earnings quality: FY25 PAT rose 55% to KES 75.5bn, with approximately 76.2% of the PBT increase attributable to higher income rather than lower provisions, supporting the underlying earnings improvement
A16: [2] Growth / balance-sheet / regional driver | B16: Returns and franchise: FY25 ROE of 26.4% was the highest among the four banks analysed, against a peer median of approximately 19.7%. Regional subsidiaries contributed about half of banking profit, supporting the Group's earnings diversification
A17: [3] Key risk or valuation consideration | B17: Valuation and risk: The justified P/B framework indicates a BUY recommendation with a KES 101.97 price target. Key risks include elevated NPLs, credit costs and potential reversal of the funding-cost tailwind. The valuation remains sensitive to the cost of equity, sustainable ROE and long-term growth assumptions

Sheet Conclusion
A1: Conclusion | B1: Summary
A2: Recommendation | B2: BUY | Target price: KES 102.00 vs. KES 69.00 at 31 March 2026 (47.8% price upside; approximately 54.6% indicative total return including a 6.8% forecast dividend yield)
A3: Investment view | B3: Equity Group's FY2025 earnings recovery, improving operating efficiency and regional diversification support a positive investment outlook. The justified P/B model indicates material upside, assuming a normalised ROE of 22% and long-term growth of 6%. However, the valuation is sensitive to the sustainability of profitability, credit costs and the cost of equity
A4: 1. Earnings recovery is supported by stronger income and efficiency | B4: FY2025 PAT increased 55% to KES 75.5bn. NII rose 17% to KES 126.9bn, supported partly by lower funding costs, while the cost-to-income ratio improved from 58.2% to 51.0%. Lower loan-loss provisions also supported earnings, meaning the exceptional profit growth should not be extrapolated indefinitely
A5: 2. Asset quality remains a key risk | B5: The gross NPL ratio declined from 13.6% in FY2024 to 11.5% in FY2025, indicating an improvement, but remained above the 8.4% recorded in FY2022. Further deterioration could increase impairment charges and weaken profitability
A6: 3. Valuation offers upside, subject to sustianable returns | B6: The justified P/B model produces a target of approximately KES 102 per share, compared with KES 69 at the valuation date. Peer P/E provides a supporting cross-check, while peer P/B indicates a more conservative valuation and the dividend-yield method produces a lower estimate. The target therefore depends on the sustainability of the assumed 22% normalised ROE and 18.87% cost of equity
A7: What would change the view to HOLD | B7: The recommendation would need reassessment if the share price approached the target, reducing the remaining upside, or if revised earnings expectations and valuation assumptions implied materially less upside. Any minimum required return should be stated as an investment hurdle rather than a universal rule
A8: What would make us more cautious | B8: (a) A renewed increase in NPLs or impairment charges; (b) slower NII growth as lower funding costs provide less support; (c) weaker regional subsidiary performance, currency losses or political disruption; and (d) sustainable ROE falling below the 22% base-case assumption or a higher required return reducing justified P/B
A9: Limitations of this analysis | B9: Valuation is as at 31 March 2026 and uses FY2025 financial results. The justified P/B model relies on assumptions for normalised ROE, long-term growth and cost of equity rather than a multi-year forecast or DCF. Peer valuations depend on the comparability and accuracy of selected peer inputs. The target is a model-derived estimate, not a guaranteed future price. The analysis is sensitive to changes in profitability and required returns. Subsequent share-price movements and financial results are excluded from the original investment decision

Sheet Financials
A1: Metric | B1: FY2022 | C1: FY2023 | D1: FY2024 | E1: FY2025 | F1: YoY / Δ (pp for ratios) | G1: Source / Notes
A2: Total assets (KES mn) | B2: 1447011 | C2: 1821435 | D2: 1804624 | E2: 1970992 | F2: =((E2/D2)-1) -> 0.092189841
A3: Gross loans (KES mn) | B3: 751100 | C3: 947500 | D3: 896900 | E3: 956000 | F3: =((E3/D3)-1) -> 0.065893634
A4: Customer deposits (KES mn) | B4: 1052162 | C4: 1358228 | D4: 1399648 | E4: 1455142 | F4: =((E4/D4)-1) -> 0.03964854
A5: Net interest income (KES mn) | B5: 85999 | C5: 104803 | D5: 108710 | E5: 126939 | F5: =((E5/D5)-1) -> 0.16768467
A6: Non-interest income (KES mn) | B6: 59936 | C6: 76881 | D6: 85072 | E6: 90801 | F6: =((E6/D6)-1) -> 0.067342957
A7: Total Operating Income | B7: =SUM(B5:B6) -> 145935 | C7: =SUM(C5:C6) -> 181684 | D7: =SUM(D5:D6) -> 193782 | E7: =SUM(E5:E6) -> 217740 | F7: =((E7/D7)-1) -> 0.12363377
A8: Operating expenses incl provisions (KES mn) | B8: 86091 | C8: 129804 | D8: 133042 | E8: 125625 | F8: =((E8/D8)-1) -> -0.055749312
A9: Loan loss provisions (KES mn) | B9: 15414 | C9: 35590 | D9: 20176 | E9: 14486 | F9: =((E9/D9)-1) -> -0.28201824
A10: Total Operating expenses excl of provisions (KES mn) | B10: =-(B8-B9) -> -70677 | C10: =-(C8-C9) -> -94214 | D10: =-(D8-D9) -> -112866 | E10: =-(E8-E9) -> -111139 | F10: =((E10/D10)-1) -> -0.015301331
A13: Profit before tax (KES mn) | B13: 59844 | C13: 51879 | D13: 60740 | E13: 92115 | F13: =((E13/D13)-1) -> 0.51654593
A14: Profit after tax (KES mn) | B14: 46103 | C14: 43737 | D14: 48823 | E14: 75548 | F14: =((E14/D14)-1) -> 0.54738545
A15: Total equity (KES mn) | B15: 182211 | C15: 218135 | D15: 246866 | E15: 326103 | F15: =((E15/D15)-1) -> 0.3209717
A16: ROE (%) | B16: =B14/B15 -> 0.25301985 | C16: =C14/((C15+B15)/2) -> 0.218496 | D16: =D14/((D15+C15)/2) -> 0.20999095 | E16: =E14/((E15+D15)/2) -> 0.26370711 | F16: =(E16-D16)*100 -> 5.3716165 | G16: FY22 uses closing equity – not comparable with FY23+. FY25 reported ROAE 26.7% (attributable basis); model uses total PAT / average total equity
A17: ROA (%) | B17: =B14/B2 -> 0.03186085 | C17: =C14/((C2+B2)/2) -> 0.026763177 | D17: =D14/((D2+C2)/2) -> 0.026928961 | E17: =E14/((E2+D2)/2) -> 0.0400189 | F17: =(E17-D17)*100 -> 1.308994 | G17: FY25 reported ROAA 4.2%; model uses total PAT / average total assets. Higher is better
A18: Cost-to-income (%) | B18: =(-B10/B7) -> 0.48430466 | C18: =(-C10/C7) -> 0.5185597 | D18: =(-D10/D7) -> 0.582438 | E18: =(-E10/E7) -> 0.51042069 | F18: =(E18-D18)*100 -> -7.2017312
A20: Gross non performing loans | B20: 63134 | C20: 114595 | D20: 121997 | E20: 110097
A21: NPL ratio (%) | B21: =B20/B3 -> 0.084055385 | C21: =C20/C3 -> 0.12094459 | D21: =D20/D3 -> 0.13602074 | E21: =E20/E3 -> 0.11516423 | F21: =(E21-D21)*100 -> -2.0856512
A25: Check: income − costs − PBT (KES mn) | B25: =B5+B6-B8-B13 -> 0 | C25: =C5+C6-C8-C13 -> 1 | D25: =D5+D6-D8-D13 -> 0 | E25: =E5+E6-E8-E13 -> 0 | G25: Should be ~0 (±100 = KES 0.1bn rounding in published figures).

Sheet KPIs
A1: KPI | B1: FY2022 | C1: FY2023 | D1: FY2024 | E1: FY2025 | F1: Trend / Comment
A2: Loan growth (%) | C2: =(Financials!C3/Financials!B3)-1 -> 0.26148316 | D2: =(Financials!D3/Financials!C3)-1 -> -0.053403694 | E2: =(Financials!E3/Financials!D3)-1 -> 0.065893634 | F2: Gross loans +26.1% (FY23), -5.3% (FY24), +6.6% (FY25). Lending was cut back in FY24 while NPLs peaked; growth resumed in FY25.
A3: Deposit growth (%) | C3: =(Financials!C4/Financials!B4)-1 -> 0.29089247 | D3: =(Financials!D4/Financials!C4)-1 -> 0.030495616 | E3: =(Financials!E4/Financials!D4)-1 -> 0.03964854 | F3: Deposits grew 29.1% in FY23 then only 3.0% and 4.0%
A4: PAT growth (%) | C4: =(Financials!C14/Financials!B14)-1 -> -0.051319871 | D4: =(Financials!D14/Financials!C14)-1 -> 0.11628598 | E4: =(Financials!E14/Financials!D14)-1 -> 0.54738545 | F4: FY25 PAT +54.7%. 76.2% of the KES 31.4bn PBT increase came from higher income, 18.2% from lower provisions and 5.4% from lower costs (see PBT Bridge). FY23 PAT fell because provisions more than doubled.
A5: ROE (%) | B5: =Financials!B16 -> 0.25301985 | C5: =Financials!C16 -> 0.218496 | D5: =Financials!D16 -> 0.20999095 | E5: =Financials!E16 -> 0.26370711 | F5: ROE 21.8% → 21.0% → 26.4% (FY23–25); FY25 is the highest in the peer set but flattered by low provisions. Compare with ~18% cost of equity (Scenarios): ROE well above COE is what justifies trading above book.
A6: ROA (%) | B6: =Financials!B17 -> 0.03186085 | C6: =Financials!C17 -> 0.026763177 | D6: =Financials!D17 -> 0.026928961 | E6: =Financials!E17 -> 0.0400189 | F6: ROA 2.7% → 4.0%. Higher is better. Rise reflects NII growth on a slow-growing asset base plus lower provisions
A7: NPL ratio (%) | B7: =Financials!B21 -> 0.084055385 | C7: =Financials!C21 -> 0.12094459 | D7: =Financials!D21 -> 0.13602074 | E7: =Financials!E21 -> 0.11516423 | F7: NPL ratio 8.4% (FY22) → 12.1% → 13.6% (peak) → 11.5% (FY25). Improving but still elevated
A8: Cost-to-income (%) | B8: =Financials!B18 -> 0.48430466 | C8: =Financials!C18 -> 0.5185597 | D8: =Financials!D18 -> 0.582438 | E8: =Financials!E18 -> 0.51042069 | F8: Cost-to-income (ex-provisions) 58.2% → 51.0%: opex fell while income grew 12%, giving operating leverage. FY23 51.8% shows ~51% is the normal level, so FY24 was the outlier
A9: Dividend per share (KES) | B9: 4 | C9: 4 | D9: 4.25 | E9: 5.75 | F9: DPS up 35% to KES 5.75 for FY25
A10: EPS (KES) | B10: 11.9 | C10: 11.12 | D10: 12.34 | E10: ='Peer Valuation'!C2 -> 19.07
A11: Dividend payout (%) | D11: =D9/D10 -> 0.34440843 | E11: =E9/E10 -> 0.30152071 | F11: Payout ~30.2% of EPS in FY25: low payout leaves room to grow capital and the dividend
A12: Cost of risk (provisions / avg gross loans) | B12: =Financials!B9/Financials!B3 -> 0.020521901 | C12: =Financials!C9/AVERAGE(Financials!B3,Financials!C3) -> 0.041905098 | D12: =Financials!D9/AVERAGE(Financials!C3,Financials!D3) -> 0.021878118 | E12: =Financials!E9/AVERAGE(Financials!D3,Financials!E3) -> 0.01563603 | F12: Cost of risk fell from 4.2% (FY23) to 1.6% (FY25). FY22 uses year-end loans. This is the single biggest swing factor in earnings; a return to ~2–3% would cut PAT materially
A13: Provisions as % of operating income | B13: =Financials!B9/(Financials!B7) -> 0.10562237 | C13: =Financials!C9/(Financials!C7) -> 0.19588957 | D13: =Financials!D9/(Financials!D7) -> 0.104117 | E13: =Financials!E9/(Financials!E7) -> 0.066528888 | F13: Provisions absorbed 19.6% of operating income in FY23 vs 6.7% in FY25
A14: NII / average total assets (NIM proxy) | B14: =Financials!B5/Financials!B2 -> 0.059432167 | C14: =Financials!C5/AVERAGE(Financials!B2,Financials!C2) -> 0.064130171 | D14: =Financials!D5/AVERAGE(Financials!C2,Financials!D2) -> 0.059960414 | E14: =Financials!E5/AVERAGE(Financials!D2,Financials!E2) -> 0.067241478 | F14: Proxy for margin (reported NIM: 7.4% FY23, 7.1% FY24). Rising in FY25 as interest expense fell; this tailwind may fade
A15: Gross loans / customer deposits (%) | B15: =Financials!B3/Financials!B4 -> 0.71386345 | C15: =Financials!C3/Financials!C4 -> 0.69760011 | D15: =Financials!D3/Financials!D4 -> 0.64080397 | E15: =Financials!E3/Financials!E4 -> 0.65698056 | F15: Low loan-to-deposit ratio implies ample liquidity but lower asset yield; headroom to lend more
A16: PBT growth (%) | C16: =Financials!C13/Financials!B13-1 -> -0.13309605 | D16: =Financials!D13/Financials!C13-1 -> 0.17080129 | E16: =Financials!E13/Financials!D13-1 -> 0.51654593 | F16: FY23 PBT fell 13% (provisions); FY25 +52%
A17: Non-interest income share of operating income | B17: =Financials!B6/(Financials!B5+Financials!B6) -> 0.4107034 | C17: =Financials!C6/(Financials!C5+Financials!C6) -> 0.42315779 | D17: =Financials!D6/(Financials!D5+Financials!D6) -> 0.43900878 | E17: =Financials!E6/(Financials!E5+Financials!E6) -> 0.41701571 | F17: ~42% of income is non-funded (fees, FX, insurance). Shows they are diversifying operations

Sheet PBT Bridge
A1: KES mn | B1: FY22 → FY23 | C1: FY23 → FY24 | D1: FY24 → FY25 | E1: Comment
A2: PBT – start | B2: =Financials!B13 -> 59844 | C2: =Financials!C13 -> 51879 | D2: =Financials!D13 -> 60740
A3: Δ Net interest income | B3: =Financials!C5-Financials!B5 -> 18804 | C3: =Financials!D5-Financials!C5 -> 3907 | D3: =Financials!E5-Financials!D5 -> 18229 | E3: FY25: NII was the largest single driver. Helped by falling funding costs, so partly rate-cycle dependent
A4: Δ Non-interest income | B4: =Financials!C6-Financials!B6 -> 16945 | C4: =Financials!D6-Financials!C6 -> 8191 | D4: =Financials!E6-Financials!D6 -> 5729 | E4: Fees, FX and insurance income: steady, diversifying growth
A5: Δ Operating expenses (excl. provisions) | B5: =Financials!C10-Financials!B10 -> -23537 | C5: =Financials!D10-Financials!C10 -> -18652 | D5: =Financials!E10-Financials!D10 -> 1727 | E5: Positive = costs fell. Opex rose steadily until FY24
A6: Δ Loan loss provisions | B6: =-(Financials!C9-Financials!B9) -> -20176 | C6: =-(Financials!D9-Financials!C9) -> 15414 | D6: =-(Financials!E9-Financials!D9) -> 5690 | E6: Positive = provisions fell. FY23 was the shock year (provisions +KES 21.9bn); FY25 provides a smaller (+KES 5.7bn) tailwind
A7: Rounding / unexplained | B7: =B8-B2-SUM(B3:B6) -> -1 | C7: =C8-C2-SUM(C3:C6) -> 1 | D7: =D8-D2-SUM(D3:D6) -> 0
A8: PBT – end | B8: =Financials!C13 -> 51879 | C8: =Financials!D13 -> 60740 | D8: =Financials!E13 -> 92115
A9: Change in PBT | B9: =B8-B2 -> -7965 | C9: =C8-C2 -> 8861 | D9: =D8-D2 -> 31375 | E9: FY23: PBT fell because provisions and costs outgrew income. FY25: ~76.2% of the increase is income-driven, so the FY25 jump is not mainly a provisions write-back
A11: FY25 change in PBT
A12: Net interest income | D12: =D3/D$9 -> 0.58100398
A13: Non-interest income | D13: =D4/D$9 -> 0.18259761
A14: Lower operating costs (excl. provisions) | D14: =D5/D$9 -> 0.055043825
A15: Lower provisions | D15: =D6/D$9 -> 0.18135458
A16: Rounding | D16: =D7/D$9 -> 0
A17: Income-driven (NII + non-interest income) | D17: =D12+D13 -> 0.76360159

Sheet NII Analysis
A1: KES mn | B1: FY2022 | C1: FY2023 | D1: FY2024 | E1: FY2025
A2: Interest Income
A3: Loans and advances | B3: 78232 | C3: 102263 | D3: 107672 | E3: 105884
A4: Government securities | B4: 40024 | C4: 51405 | D4: 56481 | E4: 60964
A5: Deposits and placements with banking instututions | B5: 1215 | C5: 1871 | D5: 5514 | E5: 5963
A6: Other Income | B6: 164 | C6: 454 | D6: 618 | E6: 827
A7: Interest Income | B7: =SUM(B3:B6) -> 119635 | C7: =SUM(C3:C6) -> 155993 | D7: =SUM(D3:D6) -> 170285 | E7: =SUM(E3:E6) -> 173638
A8: Interest Expense
A9: Customer deposits | B9: 22427 | C9: 33441 | D9: 48484 | E9: 35684
A10: Deposits and placements from banking institutions | B10: 2906 | C10: 4396 | D10: 4605 | E10: 1416
A11: Other interest expense | B11: 8303 | C11: 13353 | D11: 8486 | E11: 9599
A12: Interest Expense | B12: =SUM(B9:B11) -> 33636 | C12: =SUM(C9:C11) -> 51190 | D12: =SUM(D9:D11) -> 61575 | E12: =SUM(E9:E11) -> 46699
A13: Net Interest Income | B13: =B7-B12 -> 85999 | C13: =C7-C12 -> 104803 | D13: =D7-D12 -> 108710 | E13: =E7-E12 -> 126939
A17: Loans and advances growth | C17: =(C3/B3)-1 -> 0.30717609 | D17: =(D3/C3)-1 -> 0.052893031 | E17: =(E3/D3)-1 -> -0.016605989
A18: Government securities growth | C18: =(C4/B4)-1 -> 0.28435439 | D18: =(D4/C4)-1 -> 0.098745258 | E18: =(E4/D4)-1 -> 0.079371824
A19: Deposits and placements growth | C19: =(C5/B5)-1 -> 0.5399177 | D19: =(D5/C5)-1 -> 1.9470871 | E19: =(E5/D5)-1 -> 0.08142909
A20: Other Income growth | C20: =(C6/B6)-1 -> 1.7682927 | D20: =(D6/C6)-1 -> 0.36123348 | E20: =(E6/D6)-1 -> 0.3381877
A21: Interest Income growth | C21: =(C7/B7)-1 -> 0.30390772 | D21: =(D7/C7)-1 -> 0.091619496 | E21: =(E7/D7)-1 -> 0.019690519
A22: Customer deposits | C22: =(C9/B9)-1 -> 0.49110447 | D22: =(D9/C9)-1 -> 0.44983703 | E22: =(E9/D9)-1 -> -0.26400462
A23: Deposits and placements from banking institutions | C23: =(C10/B10)-1 -> 0.51273228 | D23: =(D10/C10)-1 -> 0.047543221 | E23: =(E10/D10)-1 -> -0.69250814
A24: Other interest expense | C24: =(C11/B11)-1 -> 0.6082139 | D24: =(D11/C11)-1 -> -0.36448738 | E24: =(E11/D11)-1 -> 0.1311572
A25: Interest Expense | C25: =(C12/B12)-1 -> 0.52188132 | D25: =(D12/C12)-1 -> 0.20287165 | E25: =(E12/D12)-1 -> -0.24159156
A26: Net Interest Income | C26: =(C13/B13)-1 -> 0.21865371 | D26: =(D13/C13)-1 -> 0.037279467 | E26: =(E13/D13)-1 -> 0.16768467

Sheet Price Performance
A1: Year | B1: EQTY Starting Price (KES) | C1: EQTY Ending Price ( KES) | D1: NSE 20 Starting | E1: NSE 20 Ending | F1: EQTY Return | G1: Benchmark Return | H1: Relative Return | I1: Comment | J1: Dividend received in year (KES) | K1: EQTY Total Return | L1: Total return − benchmark
A2: 2022 | B2: 52.75 | C2: 44.5 | D2: 1902.57 | E2: 1676.1 | F2: =(C2/B2)-1 -> -0.1563981 | G2: =(E2/D2)-1 -> -0.11903373 | H2: =F2-G2 -> -0.037364376 | I2: Shares fell with the benchmark as provisions rose, though PAT still grew 15% | J2: 3 | K2: =((C2+J2)/B2)-1 -> -0.099526066 | L2: =K2-G2 -> 0.019507662
A3: 2023 | B3: =C2 -> 44.5 | C3: 33.65 | D3: =E2 -> 1676.1 | E3: 1501.16 | F3: =(C3/B3)-1 -> -0.24382022 | G3: =(E3/D3)-1 -> -0.10437325 | H3: =F3-G3 -> -0.13944698 | I3: Worst year: provisions jumped to KES 35.6bn and PAT fell 5%; heavy KES depreciation and NPL concerns | J3: =KPIs!B9 -> 4 | K3: =((C3+J3)/B3)-1 -> -0.15393258 | L3: =K3-G3 -> -0.049559337
A4: 2024 | B4: =C3 -> 33.65 | C4: 48.3 | D4: =E3 -> 1501.16 | E4: 2010.65 | F4: =(C4/B4)-1 -> 0.43536404 | G4: =(E4/D4)-1 -> 0.33939753 | H4: =F4-G4 -> 0.095966509 | I4: Recovery year: PAT +12% and market-wide rally; EQTY outperformed the index | J4: =KPIs!C9 -> 4 | K4: =((C4+J4)/B4)-1 -> 0.55423477 | L4: =K4-G4 -> 0.21483724
A5: 2025 | B5: =C4 -> 48.3 | C5: 66.75 | D5: =E4 -> 2010.65 | E5: 3139.19 | F5: =(C5/B5)-1 -> 0.38198758 | G5: =(E5/D5)-1 -> 0.56128118 | H5: =F5-G5 -> -0.1792936 | I5: PAT +55% yet EQTY lagged the NSE 20 by ~18 points: the market gave little credit for the earnings growth. This gap is what the valuation work examines | J5: =KPIs!D9 -> 4.25 | K5: =((C5+J5)/B5)-1 -> 0.4699793 | L5: =K5-G5 -> -0.091301882
A7: Cumulative 2022 – 2025 | F7: =C5/B2-1 -> 0.26540284 | G7: =E5/D2-1 -> 0.64997346 | H7: =F7-G7 -> -0.38457061 | I7: Price-only since end-2021: EQTY ~+27% vs NSE 20 ~+65%. Including dividends EQTY is ~+74% (cols K–L); benchmark is price-only so this is not like-for-like | K7: =(1+K2)*(1+K3)*(1+K4)*(1+K5)-1 -> 0.74061994 | L7: =K7-G7 -> 0.09064648
A9: Notes: price returns exclude dividends unless stated (cols J–L). Dividend received in a year = prior-year DPS (paid ~mid-year)

Sheet Peer Valuation
A1: Company | B1: Price (KES) as of 31 March 2026 | C1: EPS (KES) | D1: P/E | E1: BVPS (KES) | F1: P/B | G1: ROE | H1: DPS (KES) | I1: Dividend Yield | J1: Notes
A2: Equity Group | B2: 69 | C2: 19.07 | D2: =B2/C2 -> 3.6182486 | E2: 82.02 | F2: =B2/E2 -> 0.84125823 | G2: =Financials!E16 -> 0.26370711 | H2: 5.75 | I2: =H2/B2 -> 0.083333333
A3: KCB Group | B3: 67.75 | C3: 20.79 | D3: =B3/C3 -> 3.2587783 | E3: 103.16 | F3: =B3/E3 -> 0.6567468 | G3: 0.225 | H3: 7 | I3: =H3/B3 -> 0.10332103
A4: Co-operative Bank | B4: 27 | C4: 5.04 | D4: =B4/C4 -> 5.3571429 | E4: 28.15 | F4: =B4/E4 -> 0.95914742 | G4: 0.191 | H4: 2.5 | I4: =H4/B4 -> 0.092592593
A5: NCBA Group | B5: 90.75 | C5: 14.2 | D5: =B5/C5 -> 6.3908451 | E5: 77.36 | F5: =B5/E5 -> 1.1730869 | G5: 0.197 | H5: 7.1 | I5: =H5/B5 -> 0.078236915
A6: Peer median (KCB, Co-op, NCBA) | D6: =MEDIAN(D3:D5) -> 5.3571429 | F6: =MEDIAN(F3:F5) -> 0.95914742 | G6: =MEDIAN(G3:G5) -> 0.197 | I6: =MEDIAN(I3:I5) -> 0.092592593
A7: Equity premium / (discount) to median | D7: =D2/D6-1 -> -0.3245936 | F7: =F2/F6-1 -> -0.1229104 | G7: =(G2-G6)*100 -> 6.6707112 | I7: =(I2-I6)*100 -> -0.92592593

Sheet Valuation
A1: Method | B1: Metric | C1: Equity Group | D1: Peer / Assumption | E1: Implied Value | H1: Notes
A2: Justified P/B (base scenario) | B2: Book value per share | C2: ='Peer Valuation'!E2 -> 82.02 | D2: =Scenarios!C5 -> 1.2432012 | E2: =C2*D2 -> 101.96737 | H2: Justified P/B from ROE, COE and growth (Scenarios sheet)
A6: Target price | E6: =E2 -> 101.96737
A7: Current price | E7: ='Peer Valuation'!B2 -> 69 | H7: 46112
A8: Upside / (Downside) | E8: =(E6-E7)/E7 -> 0.47778791
A9: Forecast dividend yield | E9: 0.069 | H9: Estimated yield using market data
A10: Expected total return (upside + yield) | E10: =E8+E9 -> 0.54678791
A11: Rating | E11: =IF(E8>=E12,"BUY",IF(E8<=E13,"SELL","HOLD")) -> BUY | H11: Rating rule: BUY ≥ +15%, SELL ≤ −10% expected total return, else HOLD.
A12: BUY if expected total return ≥ | E12: 0.15
A13: SELL if expected total return ≤ | E13: -0.1
A18: Other methods as supporting checks
A19: P/B | B19: Book value per share | C19: ='Peer Valuation'!E2 -> 82.02 | D19: =MEDIAN('Peer Valuation'!F3:F5) -> 0.95914742 | E19: =C19*D19 -> 78.669272
A20: P/E | B20: EPS | C20: ='Peer Valuation'!C2 -> 19.07 | D20: =MEDIAN('Peer Valuation'!D3:D5) -> 5.3571429 | E20: =C20*D20 -> 102.16071
A21: Dividend yield | B21: DPS | C21: ='Peer Valuation'!H2 -> 5.75 | D21: =MEDIAN('Peer Valuation'!I3:I5) -> 0.092592593 | E21: =C21/D21 -> 62.1

Sheet Scenarios
A1: Scenario assumptions | B1: Bear | C1: Base | D1: Bull | E1: Notes
A2: Normalised ROE | B2: 0.18 | C2: 0.22 | D2: 0.25 | E2: The base case is based on Equity Group's FY2022-2025 average ROE of 23.6%, adjusted for moderation from FY2025's elevated profitability, remaining above the peer median
A3: Cost of equity | B3: =C3+$B$25 -> 0.2087 | C3: =B24 -> 0.1887 | D3: =C3-$B$25 -> 0.1687
A4: Long-run growth (g) | B4: 0.05 | C4: 0.06 | D4: 0.065 | E4: Nominal long-run growth, below Kenyan nominal GDP growth.
A5: Justified P/B = (ROE − g)/(COE − g) | B5: =(B2-B4)/(B3-B4) -> 0.81915564 | C5: =(C2-C4)/(C3-C4) -> 1.2432012 | D5: =(D2-D4)/(D3-D4) -> 1.7839923 | E5: Gordon-growth justified P/B: the multiple a bank earning ROE on book deserves given COE and g.
A6: Book value per share (FY25, KES) | B6: ='Peer Valuation'!$E$2 -> 82.02 | C6: ='Peer Valuation'!$E$2 -> 82.02 | D6: ='Peer Valuation'!$E$2 -> 82.02
A7: Implied value per share (KES) | B7: =B5*B6 -> 67.187146 | C7: =C5*C6 -> 101.96737 | D7: =D5*D6 -> 146.32305
A8: vs current price | B8: =B7/'Peer Valuation'!$B$2-1 -> -0.026273253 | C8: =C7/'Peer Valuation'!$B$2-1 -> 0.47778791 | D8: =D7/'Peer Valuation'!$B$2-1 -> 1.1206239
B13: =B10/Financials!$E$15 -> 0 | C13: =C10/Financials!$E$15 -> 0 | D13: =D10/Financials!$E$15 -> 0
A16: Cost of equity build (CAPM)
A17: Input
A18: Kenyan 10-yr bond yield | B18: 0.113 | E18: Proxy for the local-currency government borrowing yield as at the valuation date
A19: Adjusted default spread | B19: 0.0637 | E19: Estimated sovereign default spread, subtracted to estimate a risk-free rate
A20: Estimated risk-free rate | B20: =B18-B19 -> 0.0493 | E20: Kenyan bond yield less the estimated default spread to reduce double-counting sovereign risk
A21: Mature Market ERP | B21: 0.0423 | E21: Implied mature-market equity risk premium derived from Damodaran's country-risk data
A22: Beta | B22: 1 | E22: Reflects financial leverage, high systemtic importance, and regional banking risk profile
A23: equity risk premium | B23: 0.0971 | E23: Damodaran's estimated additional equity risk premium for Kenya | F23: Source: Damodaran country risk premium data, updated 5 January 2026 (latest available data used); applied to the 31 March 2026 valuation date
A24: Cost of equity (base) | B24: =B20+(B22*B21)+B23 -> 0.1887
A25: Bear / bull COE spread (±) | B25: 0.02 | E25: Assumes market-level systematic risk; used as a simplifying assumption rather than a measured company beta
A27: Market-implied ROE at current price | B27: =C4+'Peer Valuation'!F2*(C3-C4) -> 0.16826993
A28: FY25 ROE (model basis) | B28: =Financials!E16 -> 0.26370711

Sheet Sensitivity
A1: P/B Assumption | B1: 0.6 | C1: 0.7 | D1: 0.8 | E1: 0.85 | F1: 0.9 | G1: 1 | H1: 1.1
A2: Book value / share | B2: ='Peer Valuation'!$E$2 -> 82.02 | C2: ='Peer Valuation'!$E$2 -> 82.02 | D2: ='Peer Valuation'!$E$2 -> 82.02 | E2: ='Peer Valuation'!$E$2 -> 82.02 | F2: ='Peer Valuation'!$E$2 -> 82.02 | G2: ='Peer Valuation'!$E$2 -> 82.02 | H2: ='Peer Valuation'!$E$2 -> 82.02
A3: Price | B3: =B1*B2 -> 49.212 | C3: =C1*C2 -> 57.414 | D3: =D1*D2 -> 65.616 | E3: =E1*E2 -> 69.717 | F3: =F1*F2 -> 73.818 | G3: =G1*G2 -> 82.02 | H3: =H1*H2 -> 90.222
A4: vs current price | B4: =B3/'Peer Valuation'!$B$2-1 -> -0.28678261 | C4: =C3/'Peer Valuation'!$B$2-1 -> -0.16791304 | D4: =D3/'Peer Valuation'!$B$2-1 -> -0.049043478 | E4: =E3/'Peer Valuation'!$B$2-1 -> 0.010391304 | F4: =F3/'Peer Valuation'!$B$2-1 -> 0.069826087 | G4: =G3/'Peer Valuation'!$B$2-1 -> 0.18869565 | H4: =H3/'Peer Valuation'!$B$2-1 -> 0.30756522
A7: Value per share (KES): normalised ROE (down) vs cost of equity (across), base g
A8: ROE ↓ / COE → | B8: 0.16 | C8: 0.17 | D8: 0.18 | E8: 0.19 | F8: 0.2
A9: 0.14 | B9: =($A9-Scenarios!$C$4)/(B$8-Scenarios!$C$4)*'Peer Valuation'!$E$2 -> 65.616 | C9: =($A9-Scenarios!$C$4)/(C$8-Scenarios!$C$4)*'Peer Valuation'!$E$2 -> 59.650909 | D9: =($A9-Scenarios!$C$4)/(D$8-Scenarios!$C$4)*'Peer Valuation'!$E$2 -> 54.68 | E9: =($A9-Scenarios!$C$4)/(E$8-Scenarios!$C$4)*'Peer Valuation'!$E$2 -> 50.473846 | F9: =($A9-Scenarios!$C$4)/(F$8-Scenarios!$C$4)*'Peer Valuation'!$E$2 -> 46.868571
A10: 0.16 | B10: =($A10-Scenarios!$C$4)/(B$8-Scenarios!$C$4)*'Peer Valuation'!$E$2 -> 82.02 | C10: =($A10-Scenarios!$C$4)/(C$8-Scenarios!$C$4)*'Peer Valuation'!$E$2 -> 74.563636 | D10: =($A10-Scenarios!$C$4)/(D$8-Scenarios!$C$4)*'Peer Valuation'!$E$2 -> 68.35 | E10: =($A10-Scenarios!$C$4)/(E$8-Scenarios!$C$4)*'Peer Valuation'!$E$2 -> 63.092308 | F10: =($A10-Scenarios!$C$4)/(F$8-Scenarios!$C$4)*'Peer Valuation'!$E$2 -> 58.585714
A11: 0.18 | B11: =($A11-Scenarios!$C$4)/(B$8-Scenarios!$C$4)*'Peer Valuation'!$E$2 -> 98.424 | C11: =($A11-Scenarios!$C$4)/(C$8-Scenarios!$C$4)*'Peer Valuation'!$E$2 -> 89.476364 | D11: =($A11-Scenarios!$C$4)/(D$8-Scenarios!$C$4)*'Peer Valuation'!$E$2 -> 82.02 | E11: =($A11-Scenarios!$C$4)/(E$8-Scenarios!$C$4)*'Peer Valuation'!$E$2 -> 75.710769 | F11: =($A11-Scenarios!$C$4)/(F$8-Scenarios!$C$4)*'Peer Valuation'!$E$2 -> 70.302857
A12: 0.2 | B12: =($A12-Scenarios!$C$4)/(B$8-Scenarios!$C$4)*'Peer Valuation'!$E$2 -> 114.828 | C12: =($A12-Scenarios!$C$4)/(C$8-Scenarios!$C$4)*'Peer Valuation'!$E$2 -> 104.38909 | D12: =($A12-Scenarios!$C$4)/(D$8-Scenarios!$C$4)*'Peer Valuation'!$E$2 -> 95.69 | E12: =($A12-Scenarios!$C$4)/(E$8-Scenarios!$C$4)*'Peer Valuation'!$E$2 -> 88.329231 | F12: =($A12-Scenarios!$C$4)/(F$8-Scenarios!$C$4)*'Peer Valuation'!$E$2 -> 82.02
A13: 0.22 | B13: =($A13-Scenarios!$C$4)/(B$8-Scenarios!$C$4)*'Peer Valuation'!$E$2 -> 131.232 | C13: =($A13-Scenarios!$C$4)/(C$8-Scenarios!$C$4)*'Peer Valuation'!$E$2 -> 119.30182 | D13: =($A13-Scenarios!$C$4)/(D$8-Scenarios!$C$4)*'Peer Valuation'!$E$2 -> 109.36 | E13: =($A13-Scenarios!$C$4)/(E$8-Scenarios!$C$4)*'Peer Valuation'!$E$2 -> 100.94769 | F13: =($A13-Scenarios!$C$4)/(F$8-Scenarios!$C$4)*'Peer Valuation'!$E$2 -> 93.737143
A14: 0.24 | B14: =($A14-Scenarios!$C$4)/(B$8-Scenarios!$C$4)*'Peer Valuation'!$E$2 -> 147.636 | C14: =($A14-Scenarios!$C$4)/(C$8-Scenarios!$C$4)*'Peer Valuation'!$E$2 -> 134.21455 | D14: =($A14-Scenarios!$C$4)/(D$8-Scenarios!$C$4)*'Peer Valuation'!$E$2 -> 123.03 | E14: =($A14-Scenarios!$C$4)/(E$8-Scenarios!$C$4)*'Peer Valuation'!$E$2 -> 113.56615 | F14: =($A14-Scenarios!$C$4)/(F$8-Scenarios!$C$4)*'Peer Valuation'!$E$2 -> 105.45429
A15: 0.26 | B15: =($A15-Scenarios!$C$4)/(B$8-Scenarios!$C$4)*'Peer Valuation'!$E$2 -> 164.04 | C15: =($A15-Scenarios!$C$4)/(C$8-Scenarios!$C$4)*'Peer Valuation'!$E$2 -> 149.12727 | D15: =($A15-Scenarios!$C$4)/(D$8-Scenarios!$C$4)*'Peer Valuation'!$E$2 -> 136.7 | E15: =($A15-Scenarios!$C$4)/(E$8-Scenarios!$C$4)*'Peer Valuation'!$E$2 -> 126.18462 | F15: =($A15-Scenarios!$C$4)/(F$8-Scenarios!$C$4)*'Peer Valuation'!$E$2 -> 117.17143
A17: Green = value above current price; red = below. Current price in Valuation!E7
A19: Reading the grid: at KES 66.75 the price is only justified if ROE stays at roughly 16% or below (red cells). Anywhere above that the shares screen cheap, which is why the ROE assumption is the key judgement

Sheet Thesis & Risks
A1: Type | B1: Point | C1: Evidence / Data | D1: Why it matters | E1: What would change the view
A2: Thesis | B2: Net Interest Income (NII) | C2: FY2025 NII benefited from lower interest expenses on placements with other banks and customer deposits, alongside lower funding costs in a declining interest-rate environment | D2: Explains the improvement in core interest earnings and identifies funding costs as an important driver of profitability | E2: Renewed deposit-cost pressure, higher funding costs or weaker interest income could limit further NII growth
A3: Thesis | B3: Earnings Recovery | C3: FY2025 PAT increased 55% to KES 75.5bn, supported by stronger income, improved operating efficiency and lower loan-loss provisions | D3: Shows how improvements in revenue and costs translated into stronger bottom-line profitability | E3: Slower income growth, rising operating expenses or higher impairment charges would weaken the earnings outlook
A4: Thesis | B4: Valuation Upside | C4: Justified P/B indicates a target price of approximately KES 102 versus KES 69 at 31 March 2026 | D4: Implies approximately 47.8% price upside under the base-case assumptions | E4: Lower sustainable ROE, a higher cost of equity or a lower market valuation would reduce the upside
A5: Thesis | B5: Regional Diversification | C5: Regional subsidiaries contributed approximately 54% of PBT in FY2024 | D5: Diversifies earnings beyond Kenya and provides additional growth opportunities | E5: Weaker subsidiary profitability, adverse currency movements or political and economic instability could reduce the benefits of diversification
A6: Risk | B6: Asset Quality | C6: Gross NPL ratio increased from 8.4% in FY2022 to 13.6% then fell to 11.5% in FY2025 | D6: Deteriorating asset quality can increase credit losses and pressure earnings | E6: A sustained reduction in NPLs and credit costs would ease this concern; further deterioration would strengthen it
A7: Risk | B7: Earnings Sustainability | C7: FY2025 loan-loss provisions fell to KES 14.5bn from KES 20.2bn in FY2024 | D7: Lower provisions supported profit growth, but this benefit may not recur at the same magnitude | E7: Sustained income growth alongside stable credit costs would support earnings quality; renewed provision increases would weaken it
A8: Risk | B8: Regional Exposure | C8: Operations across multiple African markets expose the group to different currencies, political environments and economic conditions | D8: Regional diversification creates growth opportunities but also introduces currency and country-specific risks | E8: Improved macroeconomic stability and stronger subsidiary performance would reduce the risk; material currency losses or political disruption would increase it
E9: Stable currencies and sovereign spreads; geographic mix of profits.

Sheet Sources
A1: Source | B1: Document / Page | C1: Date | D1: Link / Reference | E1: Used for
A2: Equity Group | B2: 2022-2025 Integrated Report & Financial Statements | C2: 2022-2025 | D2: Official investor relations – source of assets, loans, NPLs, equity, PBT, PAT in the template; reconcile to audited statements. | E2: Historical financials, strategy, risks
A3: NSE / market source | B3: Historical EQTY share prices | C3: 31 Dec 2025 | D3: Year-end prices and NSE 20 levels | E3: Price performance
A4: Peer annual reports | B4: KCB / Co-op / NCBA | C4: 2025/2026 | D4: Official investor relations | E4: Peer valuation / comparison
A5: Kenyan Wall Street | B5: Equity Group Posts Record KSh 75.5 Bn Profit | C5: 18 Mar 2026 | D5: https://kenyanwallstreet.com/equity-hits-record-ksh-75-5bn-profit | E5: FY25/FY24 NII, non-funded income, costs, provisions, deposits, EPS, DPS
A6: Equity Group (via africanfinancials) | B6: FY2025 Investor Briefing summary | C6: 18 Mar 2026 | D6: https://africanfinancials.com/document/ke-eqty-2025-pr-00/ | E6: FY25 headline results, ROAE 26.7%, ROAA 4.2%, CIR 51.0%
A7: Cytonn | B7: Equity Group FY2024 earnings note | C7: 2025 | D7: https://www.cytonn.com/uploads/downloads/earnings-note-fy2024-equity-group-v3.pdf | E7: FY23/FY24 NII, NFI, provisions, deposits, loan/deposit ratio
A8: Sterling Investment Bank | B8: Equity Group FY2024 earnings update | C8: 2025 | D8: https://sterlingib.com/wp-content/uploads/2025/03/Equity-Group-Holdings-FY2024-Earnings-UpdateI.pdf | E8: FY23/FY24 opex incl. provisions, CIR with/without provisions, NIM
A9: Kingdom Securities | B9: Equity Group FY2023 earnings update | C9: 2024 | D9: https://kingdomsecurities.co.ke/wp-content/uploads/2024/03/Equity-Group-Holdings-Plc-Earnings-Update-FY-2023-Kingdom-Securities-Limited.pdf | E9: FY22/FY23 P&L and deposits
A10: MarketScreener (press release) | B10: Equity Group Records $349m Net Profit in 2022 | C10: 2023 | D10: https://www.marketscreener.com/quote/stock/EQUITY-GROUP-HOLDINGS-PLC-6500740/news/Equity-Group-Records-349m-Net-Profit-in-2022-43369601/ | E10: FY22 NII, NFI, provisions, total costs, DPS growth
